setup.py
apikit/__init__.py
tornado_api_kit.egg-info/PKG-INFO
tornado_api_kit.egg-info/SOURCES.txt
tornado_api_kit.egg-info/dependency_links.txt
tornado_api_kit.egg-info/requires.txt
tornado_api_kit.egg-info/top_level.txt