Metadata-Version: 1.0
Name: tornado-api-kit
Version: 0.0.1
Summary: ('A collection of routines for building web APIs on top of Tornado web server. ',)
Home-page: https://github.com/sightio/tornado-api-kit
Author: Alexander Tereshkin
Author-email: atereshkin@y-node.com
License: BSD
Keywords: tornado api
Platform: UNKNOWN
Classifier: Development Status :: 3 - Alpha
Classifier: Topic :: Software Development
Classifier: Intended Audience :: Developers
Classifier: License :: OSI Approved :: BSD License
